zymmr_client/__init__.py
zymmr_client/auth.py
zymmr_client/client.py
zymmr_client/exceptions.py
zymmr_client/http.py
zymmr_client/models.py
zymmr_client/resources.py
zymmr_client/utils.py
zymmr_client-0.3.0.dist-info/METADATA
zymmr_client-0.3.0.dist-info/WHEEL
zymmr_client-0.3.0.dist-info/entry_points.txt
zymmr_client-0.3.0.dist-info/licenses/LICENSE
zymmr_client-0.3.0.dist-info/RECORD
