Metadata-Version: 2.4
Name: zymmr-client
Version: 0.3.0
Summary: Robust Python client for Zymmr Project Management API
Project-URL: Homepage, https://github.com/kiran-harbak/zymmr-client
Project-URL: Repository, https://github.com/kiran-harbak/zymmr-client.git
Project-URL: Issues, https://github.com/kiran-harbak/zymmr-client/issues
Author-email: Kiran Harbak <kiran.harbak@amruts.com>
License: MIT
License-File: LICENSE
Keywords: api-client,project-management,rest-api,zymmr
Classifier: Development Status :: 3 - Alpha
Classifier: Intended Audience :: Developers
Classifier: License :: OSI Approved :: MIT License
Classifier: Programming Language :: Python :: 3
Classifier: Programming Language :: Python :: 3.10
Classifier: Programming Language :: Python :: 3.11
Classifier: Programming Language :: Python :: 3.12
Classifier: Topic :: Software Development :: Libraries :: Python Modules
Requires-Python: >=3.10
Requires-Dist: requests>=2.32.5
